pr_agent/__init__.py
pr_agent/cli.py
pr_agent/cli_pip.py
pr_agent/config_loader.py
pr_agent/agent/__init__.py
pr_agent/agent/pr_agent.py
pr_agent/agent/pr_agent_local.py
pr_agent/algo/__init__.py
pr_agent/algo/cli_args.py
pr_agent/algo/file_filter.py
pr_agent/algo/git_patch_processing.py
pr_agent/algo/language_handler.py
pr_agent/algo/pr_processing.py
pr_agent/algo/token_handler.py
pr_agent/algo/types.py
pr_agent/algo/utils.py
pr_agent/algo/ai_handlers/base_ai_handler.py
pr_agent/algo/ai_handlers/langchain_ai_handler.py
pr_agent/algo/ai_handlers/litellm_ai_handler.py
pr_agent/algo/ai_handlers/openai_ai_handler.py
pr_agent/git_providers/__init__.py
pr_agent/git_providers/azuredevops_provider.py
pr_agent/git_providers/bitbucket_provider.py
pr_agent/git_providers/bitbucket_server_provider.py
pr_agent/git_providers/codecommit_client.py
pr_agent/git_providers/codecommit_provider.py
pr_agent/git_providers/gerrit_provider.py
pr_agent/git_providers/git_provider.py
pr_agent/git_providers/gitea_provider.py
pr_agent/git_providers/github_provider.py
pr_agent/git_providers/gitlab_provider.py
pr_agent/git_providers/local_git_provider.py
pr_agent/git_providers/utils.py
pr_agent/identity_providers/__init__.py
pr_agent/identity_providers/default_identity_provider.py
pr_agent/identity_providers/identity_provider.py
pr_agent/log/__init__.py
pr_agent/secret_providers/__init__.py
pr_agent/secret_providers/aws_secrets_manager_provider.py
pr_agent/secret_providers/google_cloud_storage_secret_provider.py
pr_agent/secret_providers/secret_provider.py
pr_agent/servers/__init__.py
pr_agent/servers/azuredevops_server_webhook.py
pr_agent/servers/bitbucket_app.py
pr_agent/servers/bitbucket_server_webhook.py
pr_agent/servers/gerrit_server.py
pr_agent/servers/gitea_app.py
pr_agent/servers/github_action_runner.py
pr_agent/servers/github_app.py
pr_agent/servers/github_lambda_webhook.py
pr_agent/servers/github_polling.py
pr_agent/servers/gitlab_lambda_webhook.py
pr_agent/servers/gitlab_webhook.py
pr_agent-0.3.0.dist-info/licenses/LICENSE
pr_agent-0.3.0.dist-info/METADATA
pr_agent-0.3.0.dist-info/WHEEL
pr_agent-0.3.0.dist-info/entry_points.txt
pr_agent-0.3.0.dist-info/top_level.txt
pr_agent-0.3.0.dist-info/RECORD
