Metadata-Version: 2.4
Name: pr-agent
Version: 0.3.0
Summary: QodoAI PR-Agent aims to help efficiently review and handle pull requests, by providing AI feedbacks and suggestions.
Author-email: QodoAI <tal.r@qodo.ai>
Maintainer-email: Tal Ridnik <tal.r@qodo.ai>
License:                     GNU AFFERO GENERAL PUBLIC LICENSE
Project-URL: Homepage, https://github.com/qodo-ai/pr-agent
Project-URL: Documentation, https://qodo-merge-docs.qodo.ai/
Keywords: AI,Agents,Pull Request,Automation,Code Review
Classifier: Intended Audience :: Developers
Classifier: Programming Language :: Python :: 3
Requires-Python: >=3.12
License-File: LICENSE
Requires-Dist: aiohttp==3.9.5
Requires-Dist: anthropic>=0.52.0
Requires-Dist: atlassian-python-api==3.41.4
Requires-Dist: azure-devops==7.1.0b3
Requires-Dist: azure-identity==1.15.0
Requires-Dist: boto3==1.33.6
Requires-Dist: certifi==2024.8.30
Requires-Dist: dynaconf==3.2.4
Requires-Dist: fastapi==0.111.0
Requires-Dist: GitPython==3.1.41
Requires-Dist: google-cloud-aiplatform==1.38.0
Requires-Dist: google-generativeai==0.8.3
Requires-Dist: google-cloud-storage==2.10.0
Requires-Dist: Jinja2==3.1.2
Requires-Dist: litellm==1.70.4
Requires-Dist: loguru==0.7.2
Requires-Dist: msrest==0.7.1
Requires-Dist: openai>=1.55.3
Requires-Dist: pytest==7.4.0
Requires-Dist: PyGithub==1.59.*
Requires-Dist: PyYAML==6.0.1
Requires-Dist: python-gitlab==3.15.0
Requires-Dist: retry==0.9.2
Requires-Dist: starlette-context==0.3.6
Requires-Dist: tiktoken==0.8.0
Requires-Dist: ujson==5.8.0
Requires-Dist: uvicorn==0.22.0
Requires-Dist: tenacity==8.2.3
Requires-Dist: gunicorn==22.0.0
Requires-Dist: pytest-cov==5.0.0
Requires-Dist: pydantic==2.8.2
Requires-Dist: html2text==2024.2.26
Requires-Dist: giteapy==1.0.8
Dynamic: license-file
